{
  "COAS0000001": {
    "BANK": "COASTAL LOCAL AREA BANK LTD",
    "IFSC": "COAS0000001",
    "MICR": "520652002",
    "BRANCH": "RTGS-HO",
    "ADDRESS": "D.NO.59-12-6,GRACE LINE, GHANTASALAVARI STREET, GAYATRI NAGAR, NEAR BENZ CIRCLE",
    "STATE": "ANDHRA PRADESH",
    "CONTACT": "+918662494426",
    "UPI": false,
    "RTGS": true,
    "CITY": "VIJAYAWADA",
    "CENTRE": "KRISHNA",
    "DISTRICT": "KRISHNA",
    "NEFT": true,
    "IMPS": true,
    "SWIFT": null
  },
  "COAS0000002": {
    "BANK": "COASTAL LOCAL AREA BANK LTD",
    "IFSC": "COAS0000002",
    "MICR": "NA",
    "BRANCH": "VIJAYAWADA",
    "ADDRESS": "D.NO.59-12-6,GRACE LINE,GHANTASALAVARI STREET,GAYATRI NAGAR,NEAR BENZ CIRCLE",
    "STATE": "ANDHRA PRADESH",
    "CONTACT": "+915200022494426",
    "UPI": false,
    "RTGS": true,
    "CITY": "VIJAYAWADA",
    "CENTRE": "KRISHNA",
    "DISTRICT": "KRISHNA",
    "NEFT": true,
    "IMPS": true,
    "SWIFT": null
  },
  "COAS0009999": {
    "BANK": null,
    "IFSC": "COAS0009999",
    "MICR": null,
    "BRANCH": "NEFT SERVICE CENTER",
    "ADDRESS": "D.NO.59-12-6, GRACE LINE, GHANTASALAVARI STREET, GAYATRI NAGAR, NEAR BENZ CIRCLE",
    "STATE": "ANDHRA PRADESH",
    "CONTACT": null,
    "UPI": false,
    "RTGS": true,
    "CITY": "KRISHNA",
    "CENTRE": "VIJAYAWADA",
    "DISTRICT": "VIJAYAWADA",
    "NEFT": false,
    "IMPS": true,
    "SWIFT": null
  }
}