{
  "MVCB0000001": {
    "BANK": "Sir M Visvesvaraya Co-operative Bank",
    "IFSC": "MVCB0000001",
    "MICR": null,
    "BRANCH": "KUMARAPARK WEST BRANCH",
    "ADDRESS": "20/1,1STFLOOR,BHADAGANADUBHAVAN,BADAGANADUSANGAROAD,SESHADRIPURAM,BANGALORE-560020",
    "STATE": "KARNATAKA",
    "CONTACT": "+918022956401",
    "UPI": false,
    "RTGS": true,
    "CITY": "BANGALORE",
    "CENTRE": "BANGALORE",
    "DISTRICT": "BANGALORE",
    "NEFT": true,
    "IMPS": true,
    "SWIFT": null,
    "ISO3166": "IN-KA"
  },
  "MVCB0000002": {
    "BANK": "Sir M Visvesvaraya Co-operative Bank",
    "IFSC": "MVCB0000002",
    "MICR": null,
    "BRANCH": "SHANKARMUTT ROAD BRANCH",
    "ADDRESS": "109,SHANKARMUTTROAD,SHANKARAPURAM,BANGALROE-560004",
    "STATE": "KARNATAKA",
    "CONTACT": "+918022956405",
    "UPI": false,
    "RTGS": true,
    "CITY": "BANGALORE",
    "CENTRE": "BANGALORE",
    "DISTRICT": "BANGALORE",
    "NEFT": true,
    "IMPS": true,
    "SWIFT": null,
    "ISO3166": "IN-KA"
  },
  "MVCB0000003": {
    "BANK": "Sir M Visvesvaraya Co-operative Bank",
    "IFSC": "MVCB0000003",
    "MICR": null,
    "BRANCH": "RAJAJINAGAR BRANCH",
    "ADDRESS": "1203/2,SUBRAMANYANAGARMAINROAD,RAJAJINAGARIISTAGE,BANGALORE-560010",
    "STATE": "KARNATAKA",
    "CONTACT": "+918022956406",
    "UPI": false,
    "RTGS": true,
    "CITY": "BANGALORE",
    "CENTRE": "BANGALORE",
    "DISTRICT": "BANGALORE",
    "NEFT": true,
    "IMPS": true,
    "SWIFT": null,
    "ISO3166": "IN-KA"
  },
  "MVCB0000004": {
    "BANK": "Sir M Visvesvaraya Co-operative Bank",
    "IFSC": "MVCB0000004",
    "MICR": null,
    "BRANCH": "J P NAGAR BRANCH",
    "ADDRESS": "68,OLD(668)45THCROSS,JAYANAGAR8THBLOCK,JAYANAGAR,BANGALORE-560082",
    "STATE": "KARNATAKA",
    "CONTACT": "+918022956409",
    "UPI": false,
    "RTGS": true,
    "CITY": "BANGALORE",
    "CENTRE": "BANGALORE",
    "DISTRICT": "BANGALORE",
    "NEFT": true,
    "IMPS": true,
    "SWIFT": null,
    "ISO3166": "IN-KA"
  },
  "MVCB0000005": {
    "BANK": "Sir M Visvesvaraya Co-operative Bank",
    "IFSC": "MVCB0000005",
    "MICR": null,
    "BRANCH": "BHANASHANKARI BRANCH",
    "ADDRESS": "5,4THMAINROAD,BHANKASHANKARIIIISTAGE,CKACHUKATTU,BANGALORE-560085",
    "STATE": "KARNATAKA",
    "CONTACT": "+918022956411",
    "UPI": false,
    "RTGS": true,
    "CITY": "BANGALORE",
    "CENTRE": "BANGALORE",
    "DISTRICT": "BANGALORE",
    "NEFT": true,
    "IMPS": true,
    "SWIFT": null,
    "ISO3166": "IN-KA"
  },
  "MVCB0000006": {
    "BANK": "Sir M Visvesvaraya Co-operative Bank",
    "IFSC": "MVCB0000006",
    "MICR": null,
    "BRANCH": "VIJAYANAGAR BRANCH",
    "ADDRESS": "75/1(OLDNO-60),IIICROSS,AMARAJYOTHINAGAR,NAGARABHAVIMAINROAD,BANGALORE-560040",
    "STATE": "KARNATAKA",
    "CONTACT": "+918022956413",
    "UPI": false,
    "RTGS": true,
    "CITY": "BANGALORE",
    "CENTRE": "BANGALORE",
    "DISTRICT": "BANGALORE",
    "NEFT": true,
    "IMPS": true,
    "SWIFT": null,
    "ISO3166": "IN-KA"
  },
  "MVCB0000007": {
    "BANK": "Sir M Visvesvaraya Co-operative Bank",
    "IFSC": "MVCB0000007",
    "MICR": null,
    "BRANCH": "KENGERI SETTALITE TOWN BRANCH",
    "ADDRESS": "1891,BEHINDRAILWAYSTATION,FIRSTMAINROAD,KENGERISATELLITETOWN,BANGALROE-560060",
    "STATE": "KARNATAKA",
    "CONTACT": "+918022956415",
    "UPI": false,
    "RTGS": true,
    "CITY": "BANGALORE",
    "CENTRE": "BANGALORE",
    "DISTRICT": "BANGALORE",
    "NEFT": true,
    "IMPS": true,
    "SWIFT": null,
    "ISO3166": "IN-KA"
  },
  "MVCB0000008": {
    "BANK": "Sir M Visvesvaraya Co-operative Bank",
    "IFSC": "MVCB0000008",
    "MICR": null,
    "BRANCH": "MATHIKERE BRANCH",
    "ADDRESS": "173,13THBMAINROAD,MATHIKERELAYOUT,BANGALORE-560054",
    "STATE": "KARNATAKA",
    "CONTACT": "+918022956416",
    "UPI": false,
    "RTGS": true,
    "CITY": "BANGALORE",
    "CENTRE": "BANGALORE",
    "DISTRICT": "BANGALORE",
    "NEFT": true,
    "IMPS": true,
    "SWIFT": null,
    "ISO3166": "IN-KA"
  },
  "MVCB0000009": {
    "BANK": "Sir M Visvesvaraya Co-operative Bank",
    "IFSC": "MVCB0000009",
    "MICR": null,
    "BRANCH": "BTM LAY OUT BRANCH",
    "ADDRESS": "25,100FEETRINGROAD,FIRSTPHASE,B.T.MLAYOUTIISTAGE,BANGALORE-560076",
    "STATE": "KARNATAKA",
    "CONTACT": "+918022956417",
    "UPI": false,
    "RTGS": true,
    "CITY": "BANGALORE",
    "CENTRE": "BANGALORE",
    "DISTRICT": "BANGALORE",
    "NEFT": true,
    "IMPS": true,
    "SWIFT": null,
    "ISO3166": "IN-KA"
  },
  "MVCB0000010": {
    "BANK": "Sir M Visvesvaraya Co-operative Bank",
    "IFSC": "MVCB0000010",
    "MICR": null,
    "BRANCH": "CORPORATE OFFICE",
    "ADDRESS": "109, SHANKARMUTT ROAD, SHANKARAPURAM, BANGALROE-560004",
    "STATE": "KARNATAKA",
    "CONTACT": "+918026611141",
    "UPI": false,
    "RTGS": true,
    "CITY": "BANGALORE",
    "CENTRE": "BANGALORE",
    "DISTRICT": "BANGALORE",
    "NEFT": false,
    "IMPS": true,
    "SWIFT": null,
    "ISO3166": "IN-KA"
  },
  "MVCB0000011": {
    "BANK": "Sir M Visvesvaraya Co-operative Bank",
    "IFSC": "MVCB0000011",
    "MICR": null,
    "BRANCH": "RAJARAJESWARI NAGAR BRANCH",
    "ADDRESS": "1,BEML3RDSTAGE,BEMLLAYOUT,RAJAJESWARINAGAR,BANGALORE-560098",
    "STATE": "KARNATAKA",
    "CONTACT": "+918022956421",
    "UPI": false,
    "RTGS": true,
    "CITY": "BANGALORE",
    "CENTRE": "BANGALORE",
    "DISTRICT": "BANGALORE",
    "NEFT": true,
    "IMPS": true,
    "SWIFT": null,
    "ISO3166": "IN-KA"
  },
  "MVCB0000012": {
    "BANK": "Sir M Visvesvaraya Co-operative Bank",
    "IFSC": "MVCB0000012",
    "MICR": null,
    "BRANCH": "KONANAKUNTE BRANCH",
    "ADDRESS": "100,CHUNCHGHATTAMAINROAD,KCCIRCLE,KONANAKUNTE,BANGALORE-560062",
    "STATE": "KARNATAKA",
    "CONTACT": "+918022956422",
    "UPI": false,
    "RTGS": true,
    "CITY": "BANGALORE",
    "CENTRE": "BANGALORE",
    "DISTRICT": "BANGALORE",
    "NEFT": true,
    "IMPS": true,
    "SWIFT": null,
    "ISO3166": "IN-KA"
  }
}