{
  "NCUB0000001": {
    "BANK": "Nilambur Co-operative Urban Bank",
    "IFSC": "NCUB0000001",
    "MICR": "679792102",
    "BRANCH": "RTGS-HO",
    "ADDRESS": "P.B.NO.10,NILAMBUR MAIN ROAD,NILAMBUR",
    "STATE": "KERALA",
    "CONTACT": "+914931220227",
    "UPI": false,
    "RTGS": true,
    "CITY": "NILAMBUR",
    "CENTRE": "MALAPPURAM",
    "DISTRICT": "MALAPPURAM",
    "NEFT": true,
    "IMPS": true,
    "SWIFT": null,
    "ISO3166": "IN-KL"
  },
  "NCUB0000002": {
    "BANK": "Nilambur Co-operative Urban Bank",
    "IFSC": "NCUB0000002",
    "MICR": "679792103",
    "BRANCH": "WANDOOR MAIN BRANCH",
    "ADDRESS": "NILAMBUR ROAD,P.O.WANDOOR,PIN 679328",
    "STATE": "KERALA",
    "CONTACT": "+914931247051",
    "UPI": false,
    "RTGS": true,
    "CITY": "WANDOOR",
    "CENTRE": "MALAPPURAM",
    "DISTRICT": "MALAPPURAM",
    "NEFT": true,
    "IMPS": true,
    "SWIFT": null,
    "ISO3166": "IN-KL"
  },
  "NCUB0000003": {
    "BANK": "Nilambur Co-operative Urban Bank",
    "IFSC": "NCUB0000003",
    "MICR": "679792104",
    "BRANCH": "KALIKAVU BRANCH",
    "ADDRESS": "KALIKAVU JUNCTION,KALIKAVU P.O.PIN 676525",
    "STATE": "KERALA",
    "CONTACT": "+914931257252",
    "UPI": false,
    "RTGS": true,
    "CITY": "KALIKAVU",
    "CENTRE": "MALAPPURAM",
    "DISTRICT": "MALAPPURAM",
    "NEFT": true,
    "IMPS": true,
    "SWIFT": null,
    "ISO3166": "IN-KL"
  },
  "NCUB0000004": {
    "BANK": "Nilambur Co-operative Urban Bank",
    "IFSC": "NCUB0000004",
    "MICR": "679792105",
    "BRANCH": "CHUNGATHARA BRANCH",
    "ADDRESS": "MAIN ROAD,P.O.CHUNGATHARA,PIN 679334",
    "STATE": "KERALA",
    "CONTACT": "+914931230250",
    "UPI": false,
    "RTGS": true,
    "CITY": "CHUNGATHARA",
    "CENTRE": "MALAPPURAM",
    "DISTRICT": "MALAPPURAM",
    "NEFT": true,
    "IMPS": true,
    "SWIFT": null,
    "ISO3166": "IN-KL"
  },
  "NCUB0000005": {
    "BANK": "Nilambur Co-operative Urban Bank",
    "IFSC": "NCUB0000005",
    "MICR": "679792152",
    "BRANCH": "KARUVARAKUNDU BRANCH",
    "ADDRESS": "KIZHAKKETHALA,THARISSU P.O.PIN 676523",
    "STATE": "KERALA",
    "CONTACT": "+914931280270",
    "UPI": false,
    "RTGS": true,
    "CITY": "KARUVARAKUNDU",
    "CENTRE": "MALAPPURAM",
    "DISTRICT": "MALAPPURAM",
    "NEFT": true,
    "IMPS": true,
    "SWIFT": null,
    "ISO3166": "IN-KL"
  },
  "NCUB0000006": {
    "BANK": "Nilambur Co-operative Urban Bank",
    "IFSC": "NCUB0000006",
    "MICR": "679792106",
    "BRANCH": "POOKKOTTUMPADAM BRANCH",
    "ADDRESS": "MAIN ROAD,POOKOTTUMPADAM.P.O.PIN 679332",
    "STATE": "KERALA",
    "CONTACT": "+914931260307",
    "UPI": false,
    "RTGS": true,
    "CITY": "POOKKOTTUMPADAM",
    "CENTRE": "MALAPPURAM",
    "DISTRICT": "MALAPPURAM",
    "NEFT": true,
    "IMPS": true,
    "SWIFT": null,
    "ISO3166": "IN-KL"
  },
  "NCUB0000007": {
    "BANK": "Nilambur Co-operative Urban Bank",
    "IFSC": "NCUB0000007",
    "MICR": "679792107",
    "BRANCH": "EDAKKARA MAIN BRANCH",
    "ADDRESS": "MAIN ROAD,EDAKKARA,PIN 679331",
    "STATE": "KERALA",
    "CONTACT": "+914931276008",
    "UPI": false,
    "RTGS": true,
    "CITY": "EDAKKARA",
    "CENTRE": "MALAPPURAM",
    "DISTRICT": "MALAPPURAM",
    "NEFT": true,
    "IMPS": true,
    "SWIFT": null,
    "ISO3166": "IN-KL"
  },
  "NCUB0000008": {
    "BANK": "Nilambur Co-operative Urban Bank",
    "IFSC": "NCUB0000008",
    "MICR": "679792153",
    "BRANCH": "PANDIKKAD BRANCH",
    "ADDRESS": "PERINTHALMANNA ROAD,PANDIKKAD.P.O.PIN 676521",
    "STATE": "KERALA",
    "CONTACT": "+914832783485",
    "UPI": false,
    "RTGS": true,
    "CITY": "PANDIKKAD",
    "CENTRE": "MALAPPURAM",
    "DISTRICT": "MALAPPURAM",
    "NEFT": true,
    "IMPS": true,
    "SWIFT": null,
    "ISO3166": "IN-KL"
  },
  "NCUB0000009": {
    "BANK": "Nilambur Co-operative Urban Bank",
    "IFSC": "NCUB0000009",
    "MICR": "679792108",
    "BRANCH": "AKAMPADAM BRANCH",
    "ADDRESS": "ERANHIMANGAD.P.O,PIN 679541",
    "STATE": "KERALA",
    "CONTACT": "+914931206373",
    "UPI": false,
    "RTGS": true,
    "CITY": "AKAMPADAM",
    "CENTRE": "MALAPPURAM",
    "DISTRICT": "MALAPPURAM",
    "NEFT": true,
    "IMPS": true,
    "SWIFT": null,
    "ISO3166": "IN-KL"
  },
  "NCUB0000010": {
    "BANK": "Nilambur Co-operative Urban Bank",
    "IFSC": "NCUB0000010",
    "MICR": "676792053",
    "BRANCH": "EDAVANNA BRANCH",
    "ADDRESS": "MANJERI ROAD,P.O.EDAVANNA,PIN 676541",
    "STATE": "KERALA",
    "CONTACT": "+914832700743",
    "UPI": false,
    "RTGS": true,
    "CITY": "EDAVANNA",
    "CENTRE": "MALAPPURAM",
    "DISTRICT": "MALAPPURAM",
    "NEFT": true,
    "IMPS": true,
    "SWIFT": null,
    "ISO3166": "IN-KL"
  },
  "NCUB0000011": {
    "BANK": "Nilambur Co-operative Urban Bank",
    "IFSC": "NCUB0000011",
    "MICR": "679792109",
    "BRANCH": "NILAMBUR EVENING BRANCH",
    "ADDRESS": "MAIN ROAD,NILAMBUR,PIN 679329",
    "STATE": "KERALA",
    "CONTACT": "+914931221849",
    "UPI": false,
    "RTGS": true,
    "CITY": "NILAMBUR",
    "CENTRE": "MALAPPURAM",
    "DISTRICT": "MALAPPURAM",
    "NEFT": true,
    "IMPS": true,
    "SWIFT": null,
    "ISO3166": "IN-KL"
  },
  "NCUB0000012": {
    "BANK": "Nilambur Co-operative Urban Bank",
    "IFSC": "NCUB0000012",
    "MICR": "679792110",
    "BRANCH": "KARULAI BRANCH",
    "ADDRESS": "KARULAI P.O.PIN 679344",
    "STATE": "KERALA",
    "CONTACT": "+914931270501",
    "UPI": false,
    "RTGS": true,
    "CITY": "KARULAI",
    "CENTRE": "MALAPPURAM",
    "DISTRICT": "MALAPPURAM",
    "NEFT": true,
    "IMPS": true,
    "SWIFT": null,
    "ISO3166": "IN-KL"
  },
  "NCUB0000013": {
    "BANK": "Nilambur Co-operative Urban Bank",
    "IFSC": "NCUB0000013",
    "MICR": "679792111",
    "BRANCH": "EDAKKARA EVENING BRANCH",
    "ADDRESS": "MAIN ROAD,EDAKKARA.P.O.PIN 679331",
    "STATE": "KERALA",
    "CONTACT": "+914931277007",
    "UPI": false,
    "RTGS": true,
    "CITY": "EDAKKARA",
    "CENTRE": "MALAPPURAM",
    "DISTRICT": "MALAPPURAM",
    "NEFT": true,
    "IMPS": true,
    "SWIFT": null,
    "ISO3166": "IN-KL"
  },
  "NCUB0000014": {
    "BANK": "Nilambur Co-operative Urban Bank",
    "IFSC": "NCUB0000014",
    "MICR": "679792112",
    "BRANCH": "WANDOOR EVENING BRANCH",
    "ADDRESS": "KALIKAVU ROAD,WANDOOR.P.O,PIN 679328",
    "STATE": "KERALA",
    "CONTACT": "+914931246051",
    "UPI": false,
    "RTGS": true,
    "CITY": "WANDOOR",
    "CENTRE": "MALAPPURAM",
    "DISTRICT": "MALAPPURAM",
    "NEFT": true,
    "IMPS": true,
    "SWIFT": null,
    "ISO3166": "IN-KL"
  },
  "NCUB0000015": {
    "BANK": "Nilambur Co-operative Urban Bank",
    "IFSC": "NCUB0000015",
    "MICR": "679792113",
    "BRANCH": "POTHUKAL BRANCH",
    "ADDRESS": "POTHUKAL P.O,PIN 679334",
    "STATE": "KERALA",
    "CONTACT": "+914931241800",
    "UPI": false,
    "RTGS": true,
    "CITY": "POTHUKAL",
    "CENTRE": "MALAPPURAM",
    "DISTRICT": "MALAPPURAM",
    "NEFT": true,
    "IMPS": true,
    "SWIFT": null,
    "ISO3166": "IN-KL"
  },
  "NCUB0000016": {
    "BANK": "Nilambur Co-operative Urban Bank",
    "IFSC": "NCUB0000016",
    "MICR": "679792154",
    "BRANCH": "TUWUR BRANCH",
    "ADDRESS": "THUVVUR P.O,PIN 679327",
    "STATE": "KERALA",
    "CONTACT": "+914931285222",
    "UPI": false,
    "RTGS": true,
    "CITY": "TUWUR",
    "CENTRE": "MALAPPURAM",
    "DISTRICT": "MALAPPURAM",
    "NEFT": true,
    "IMPS": true,
    "SWIFT": null,
    "ISO3166": "IN-KL"
  },
  "NCUB0000017": {
    "BANK": "Nilambur Co-operative Urban Bank",
    "IFSC": "NCUB0000017",
    "MICR": "679792114",
    "BRANCH": "VAZHIKKADAVU BRANCH",
    "ADDRESS": "VAZHIKADAVU POST,PANCHAYATHUMPADI,MALAPPURA-DIST,KERALA",
    "STATE": "KERALA",
    "CONTACT": "+914931274490",
    "UPI": false,
    "RTGS": true,
    "CITY": "VAZHIKKADAVU",
    "CENTRE": "MALAPPURAM",
    "DISTRICT": "MALAPPURAM",
    "NEFT": true,
    "IMPS": true,
    "SWIFT": null,
    "ISO3166": "IN-KL"
  },
  "NCUB0000018": {
    "BANK": "Nilambur Co-operative Urban Bank",
    "IFSC": "NCUB0000018",
    "MICR": "676792054",
    "BRANCH": "THRIKKALANGODE BRANCH",
    "ADDRESS": "ROOM NO.343,WARD NO.2,THRIKKALANGODE TOWN-32,MALAPPURAM DIST - 676123",
    "STATE": "KERALA",
    "CONTACT": "+914832840089",
    "UPI": false,
    "RTGS": true,
    "CITY": "THRIKKALANGODE",
    "CENTRE": "MALAPPURAM",
    "DISTRICT": "MALAPPURAM",
    "NEFT": true,
    "IMPS": true,
    "SWIFT": null,
    "ISO3166": "IN-KL"
  },
  "NCUB0000019": {
    "BANK": "Nilambur Co-operative Urban Bank",
    "IFSC": "NCUB0000019",
    "MICR": "676792055",
    "BRANCH": "THIRUVALI BRANCH",
    "ADDRESS": "BUILDING NO.558 A,SREERAGAM BUILDINGWARD NO.12,THIRUVALI POST,MALAPPURAM DIST - 676123",
    "STATE": "KERALA",
    "CONTACT": "+914832720023",
    "UPI": false,
    "RTGS": true,
    "CITY": "THIRUVALI",
    "CENTRE": "MALAPPURAM",
    "DISTRICT": "MALAPPURAM",
    "NEFT": true,
    "IMPS": true,
    "SWIFT": null,
    "ISO3166": "IN-KL"
  },
  "NCUB0000020": {
    "BANK": "Nilambur Co-operative Urban Bank",
    "IFSC": "NCUB0000020",
    "MICR": "679792155",
    "BRANCH": "KARUVARAKUNDU EVENING BRANCH",
    "ADDRESS": "BUILDING NO.1036,MARANATTU PLACEWARD NO.10,KIZHAKKETHALA POST,MALAPPURAM DIST - 676523",
    "STATE": "KERALA",
    "CONTACT": "+914931282270",
    "UPI": false,
    "RTGS": true,
    "CITY": "KARUVARAKUNDU",
    "CENTRE": "MALAPPURAM",
    "DISTRICT": "MALAPPURAM",
    "NEFT": true,
    "IMPS": true,
    "SWIFT": null,
    "ISO3166": "IN-KL"
  },
  "NCUB0000021": {
    "BANK": "Nilambur Co-operative Urban Bank",
    "IFSC": "NCUB0000021",
    "MICR": "679792115",
    "BRANCH": "CHERUKODE BRANCH",
    "ADDRESS": "BUILDING NO.1 - 28 B,ELAYODAN BUILDING,CHATHANGOTTUPURAM POST,MALAPPURAM DIST - 679328",
    "STATE": "KERALA",
    "CONTACT": "+914931245021",
    "UPI": false,
    "RTGS": true,
    "CITY": "CHERUKODE",
    "CENTRE": "MALAPPURAM",
    "DISTRICT": "MALAPPURAM",
    "NEFT": true,
    "IMPS": true,
    "SWIFT": null,
    "ISO3166": "IN-KL"
  },
  "NCUB0000022": {
    "BANK": "Nilambur Co-operative Urban Bank",
    "IFSC": "NCUB0000022",
    "MICR": "679792116",
    "BRANCH": "CHOKKAD BRANCH",
    "ADDRESS": "BUILDING NO.156,PKG BUILDING,CHOKKAD POST,MALAPPURAM DIST - 679355",
    "STATE": "KERALA",
    "CONTACT": "+914931261322",
    "UPI": false,
    "RTGS": true,
    "CITY": "CHOKKAD",
    "CENTRE": "MALAPPURAM",
    "DISTRICT": "MALAPPURAM",
    "NEFT": true,
    "IMPS": true,
    "SWIFT": null,
    "ISO3166": "IN-KL"
  },
  "NCUB0000023": {
    "BANK": "Nilambur Co-operative Urban Bank",
    "IFSC": "NCUB0000023",
    "MICR": "679792117",
    "BRANCH": "MAMPAD BRANCH",
    "ADDRESS": "WEE THREE TOWER,MAMPAD POST,MAMPAD -676542,MALAPPURAM",
    "STATE": "KERALA",
    "CONTACT": "+914931201023",
    "UPI": false,
    "RTGS": true,
    "CITY": "MAMPAD",
    "CENTRE": "MALAPPURAM",
    "DISTRICT": "MALAPPURAM",
    "NEFT": true,
    "IMPS": true,
    "SWIFT": null,
    "ISO3166": "IN-KL"
  },
  "NCUB0000024": {
    "BANK": "Nilambur Co-operative Urban Bank",
    "IFSC": "NCUB0000024",
    "MICR": "679792118",
    "BRANCH": "ERUMAMUNDA BRANCH",
    "ADDRESS": "ROOM NO 572 B,WARD 20,ERUMAMUNDA POST,MALAPPURAM DIST -679334",
    "STATE": "KERALA",
    "CONTACT": "+914931255024",
    "UPI": false,
    "RTGS": true,
    "CITY": "ERUMAMUNDA",
    "CENTRE": "MALAPPURAM",
    "DISTRICT": "MALAPPURAM",
    "NEFT": true,
    "IMPS": true,
    "SWIFT": null,
    "ISO3166": "IN-KL"
  },
  "NCUB0000025": {
    "BANK": "Nilambur Co-operative Urban Bank",
    "IFSC": "NCUB0000025",
    "MICR": "679792119",
    "BRANCH": "VANIYAMBALAM BRANCH",
    "ADDRESS": "ALSALAMA BUILDING,VANIYAMBALAM PO,PIN 679339,PHONE 04931-235025",
    "STATE": "KERALA",
    "CONTACT": "+914931235025",
    "UPI": false,
    "RTGS": true,
    "CITY": "VANIYAMBALAM",
    "CENTRE": "MALAPPURAM",
    "DISTRICT": "MALAPPURAM",
    "NEFT": true,
    "IMPS": true,
    "SWIFT": null,
    "ISO3166": "IN-KL"
  },
  "NCUB0000026": {
    "BANK": "Nilambur Co-operative Urban Bank",
    "IFSC": "NCUB0000026",
    "MICR": "679792120",
    "BRANCH": "KARAPPURAM BRANCH",
    "ADDRESS": "BUILDING NO 588,PKS BUILDING,MOOTHEDAM PO,MALAPPUARAM 679331",
    "STATE": "KERALA",
    "CONTACT": "+914931277026",
    "UPI": false,
    "RTGS": true,
    "CITY": "KARAPPURAM",
    "CENTRE": "MALAPPURAM",
    "DISTRICT": "MALAPPURAM",
    "NEFT": true,
    "IMPS": true,
    "SWIFT": null,
    "ISO3166": "IN-KL"
  },
  "NCUB0000100": {
    "BANK": "Nilambur Co-operative Urban Bank",
    "IFSC": "NCUB0000100",
    "MICR": null,
    "BRANCH": "HEAD OFFICE",
    "ADDRESS": "NILAMBUR PO,MALAPPURAM DISTRICT,KERALA,PIN 679329",
    "STATE": "KERALA",
    "CONTACT": "+914931220142",
    "UPI": false,
    "RTGS": true,
    "CITY": "NILAMBUR",
    "CENTRE": "MALAPPURAM",
    "DISTRICT": "MALAPPURAM",
    "NEFT": true,
    "IMPS": true,
    "SWIFT": null,
    "ISO3166": "IN-KL"
  },
  "NCUB0000101": {
    "BANK": "Nilambur Co-operative Urban Bank",
    "IFSC": "NCUB0000101",
    "MICR": null,
    "BRANCH": "NILAMBUR MAIN BRANCH",
    "ADDRESS": "P.B.NO.10,NILAMBUR MAIN ROAD,NILAMBUR",
    "STATE": "KERALA",
    "CONTACT": "+914931220227",
    "UPI": false,
    "RTGS": true,
    "CITY": "NILAMBUR",
    "CENTRE": "MALAPPURAM",
    "DISTRICT": "MALAPPURAM",
    "NEFT": true,
    "IMPS": true,
    "SWIFT": null,
    "ISO3166": "IN-KL"
  }
}