{
  "SUTB0000001": {
    "BANK": "SUTEX COOPERATIVE BANK LIMITED",
    "IFSC": "SUTB0000001",
    "BRANCH": "RTGS-HO",
    "ADDRESS": "2ND FLOOR, SURAJRAM BACHKANIWALA BHAVAN,NR.NAVJIVAN CIRCLE,UDHNA MAGDALLA RD., SURAT-395017,GUJARAT (INDIA)",
    "CONTACT": "2632519",
    "CITY": "SURAT",
    "DISTRICT": "SURAT",
    "STATE": "GUJARAT"
  },
  "SUTB0248002": {
    "BANK": "SUTEX COOPERATIVE BANK LIMITED",
    "IFSC": "SUTB0248002",
    "BRANCH": "SURAT TEXTILE MARKET",
    "ADDRESS": "2ND FLOOR., BANK BLOCK, SURAT TEXTILE MARKET,RING ROAD, SURAT-395002,GUJARAT (INDIA).",
    "CONTACT": "2333948",
    "CITY": "SURAT",
    "DISTRICT": "SURAT",
    "STATE": "GUJARAT"
  },
  "SUTB0248003": {
    "BANK": "SUTEX COOPERATIVE BANK LIMITED",
    "IFSC": "SUTB0248003",
    "BRANCH": "STATION ROAD",
    "ADDRESS": "MEGHANI MANSION GR.FLR.,STATION ROAD, SURAT-395003,GUJARAT (INDIA).",
    "CONTACT": "2402736",
    "CITY": "SURAT",
    "DISTRICT": "SURAT",
    "STATE": "GUJARAT"
  },
  "SUTB0248004": {
    "BANK": "SUTEX COOPERATIVE BANK LIMITED",
    "IFSC": "SUTB0248004",
    "BRANCH": "KATARGAM",
    "ADDRESS": "163-B,OLD GIDC, KATARGAM,SURAT-395004, GUJARAT (INDIA).",
    "CONTACT": "2407876",
    "CITY": "SURAT",
    "DISTRICT": "SURAT",
    "STATE": "GUJARAT"
  },
  "SUTB0248005": {
    "BANK": "SUTEX COOPERATIVE BANK LIMITED",
    "IFSC": "SUTB0248005",
    "BRANCH": "GOPIPURA",
    "ADDRESS": "SUBHASH CHOWK, GOPIPURA,SURAT-395003,GUJARAT (INDIA).",
    "CONTACT": "2593059",
    "CITY": "SURAT",
    "DISTRICT": "SURAT",
    "STATE": "GUJARAT"
  },
  "SUTB0248006": {
    "BANK": "SUTEX COOPERATIVE BANK LIMITED",
    "IFSC": "SUTB0248006",
    "BRANCH": "RANDER ROAD",
    "ADDRESS": "BESIDE AASHIRWAD SOC., NR.NAVYUG COLLEGE,RANDER ROAD, SURAT-395009,GUJARAT (INDIA).",
    "CONTACT": "2781989",
    "CITY": "SURAT",
    "DISTRICT": "SURAT",
    "STATE": "GUJARAT"
  },
  "SUTB0248007": {
    "BANK": "SUTEX COOPERATIVE BANK LIMITED",
    "IFSC": "SUTB0248007",
    "BRANCH": "VARACHHA ROAD",
    "ADDRESS": "GR.FLR., SHREYAS DIAMOND CENTRE,VARACHHA ROAD, SURAT-395006,GUJARAT (INDIA).",
    "CONTACT": "2541876",
    "CITY": "SURAT",
    "DISTRICT": "SURAT",
    "STATE": "GUJARAT"
  },
  "SUTB0248008": {
    "BANK": "SUTEX COOPERATIVE BANK LIMITED",
    "IFSC": "SUTB0248008",
    "BRANCH": "ATHWALINES",
    "ADDRESS": "ANJAN SALAKHA BLDG., NR.NEW DIST.COURT BLDG., ATHWALINES, SURAT-395001,GUJARAT (INDIA).",
    "CONTACT": "2254568",
    "CITY": "SURAT",
    "DISTRICT": "SURAT",
    "STATE": "GUJARAT"
  },
  "SUTB0248009": {
    "BANK": "SUTEX COOPERATIVE BANK LIMITED",
    "IFSC": "SUTB0248009",
    "BRANCH": "UDHNA MAGDALLA ROAD",
    "ADDRESS": "SURAJRAM BACHKANIWALA BHAVAN, GR.FLOOR,UDHNA-MAGDALLA RD., SURAT-395017,GUJARAT (INDIA).",
    "CONTACT": "2630519",
    "CITY": "SURAT",
    "DISTRICT": "SURAT",
    "STATE": "GUJARAT"
  },
  "SUTB0248010": {
    "BANK": "SUTEX COOPERATIVE BANK LIMITED",
    "IFSC": "SUTB0248010",
    "BRANCH": "SACHIN GIDC",
    "ADDRESS": "PLOT NO.1008, SACHIN GIDC,DIST.SURAT-394230,GUJARAT (INDIA).",
    "CONTACT": "2397954",
    "CITY": "SURAT",
    "DISTRICT": "SURAT",
    "STATE": "GUJARAT"
  },
  "SUTB0248011": {
    "BANK": "SUTEX COOPERATIVE BANK LIMITED",
    "IFSC": "SUTB0248011",
    "BRANCH": "PARVAT PATIA",
    "ADDRESS": "1ST FLR., SURBHI COMPLEX, NR.POONA OCTROI NAKA, PARVAT PATIA, SURAT-394210, GUJARAT (INDIA).",
    "CONTACT": "2641495",
    "CITY": "SURAT",
    "DISTRICT": "SURAT",
    "STATE": "GUJARAT"
  },
  "SUTB0248013": {
    "BANK": "SUTEX COOPERATIVE BANK LIMITED",
    "IFSC": "SUTB0248013",
    "BRANCH": "CITY LIGHT",
    "ADDRESS": "UG1 TO UG7, HIRA PANNA SHOPPING MALL, NR.MAHESHWARY BHAVAN,CITY LIGHT ROAD, SURAT-395007, GUJARAT (INDIA).",
    "CONTACT": "2256444",
    "CITY": "SURAT",
    "DISTRICT": "SURAT",
    "STATE": "GUJARAT"
  },
  "SUTB0248014": {
    "BANK": "SUTEX COOPERATIVE BANK LIMITED",
    "IFSC": "SUTB0248014",
    "BRANCH": "SALABATPURA",
    "ADDRESS": "3/2249-B, PIPARDI SHERI,SALABATPURA,SURAT-395003,GUJARAT (INDIA).",
    "CONTACT": "2365608",
    "CITY": "SURAT",
    "DISTRICT": "SURAT",
    "STATE": "GUJARAT"
  },
  "SUTB0248015": {
    "BANK": "SUTEX COOPERATIVE BANK LIMITED",
    "IFSC": "SUTB0248015",
    "BRANCH": "PANDESARA GIDC",
    "ADDRESS": "PLOT NO.C-196, KEVAL COMMERCIAL COMPLEX, PANDESARA MAIN RD, SURAT-394221,GUJARAT (INDIA).",
    "CONTACT": "2894024",
    "CITY": "SURAT",
    "DISTRICT": "SURAT",
    "STATE": "GUJARAT"
  },
  "SUTB0248016": {
    "BANK": "SUTEX COOPERATIVE BANK LIMITED",
    "IFSC": "SUTB0248016",
    "BRANCH": "SAHARA DARWAJA",
    "ADDRESS": "G-101, PARKING FLOOR, NEW TEXTILE MARKET,SAHARA DARWAJA, SURAT-395002,GUJARAT (INDIA).",
    "CONTACT": "2343940",
    "CITY": "SURAT",
    "DISTRICT": "SURAT",
    "STATE": "GUJARAT"
  },
  "SUTB0248017": {
    "BANK": "SUTEX COOPERATIVE BANK LIMITED",
    "IFSC": "SUTB0248017",
    "BRANCH": "UDHNA MAIN ROAD",
    "ADDRESS": "SHOP NO 7 BY 8 BY 8 BY 9 UPPER GROUND FLOOR,SHREENATH CHEMEBRS,UDHNA SURAT-394210,GUJARAT (INDIA)",
    "CONTACT": "2273323",
    "CITY": "SURAT",
    "DISTRICT": "SURAT",
    "STATE": "GUJARAT"
  },
  "SUTB0248018": {
    "BANK": "SUTEX COOPERATIVE BANK LIMITED",
    "IFSC": "SUTB0248018",
    "BRANCH": "ADAJAN-PAL RAOD",
    "ADDRESS": "1ST FLOOR, J-9 CENTRE, NEAR STAR BAZAAR, ADAJAN ROAD",
    "CONTACT": null,
    "CITY": "SURAT",
    "DISTRICT": "SURAT",
    "STATE": "GUJARAT"
  },
  "SUTB0248019": {
    "BANK": "SUTEX COOPERATIVE BANK LIMITED",
    "IFSC": "SUTB0248019",
    "BRANCH": "VESU",
    "ADDRESS": "G-1, SHUBH UNIVERSAL, OPP- VIJYALAXMI HALL, VESU, SURAT 395007",
    "CONTACT": null,
    "CITY": "SURAT",
    "DISTRICT": "SURAT",
    "STATE": "GUJARAT"
  },
  "SUTB0248020": {
    "BANK": "SUTEX COOPERATIVE BANK LIMITED",
    "IFSC": "SUTB0248020",
    "BRANCH": "JAHANGIRPURA",
    "ADDRESS": "SHOP NO 26-27 , GR.FLOOR , EXIITO COMMERCIAL HUB, JAHANGIRPURA, SURAT - 395005",
    "CONTACT": null,
    "CITY": "SURAT",
    "DISTRICT": "SURAT",
    "STATE": "GUJARAT"
  }
}