{
  "VTBJ0000001": {
    "BANK": null,
    "IFSC": "VTBJ0000001",
    "MICR": null,
    "BRANCH": "RTGS-HO",
    "ADDRESS": "JSC VTB BANK, TAJ MAHAL HOTEL, LOBBY MEZZANINE FLOOR 1, MANSINGH ROAD NEW DELHI- 110011",
    "STATE": "DELHI",
    "CONTACT": "+9111662210000",
    "UPI": false,
    "RTGS": true,
    "CITY": "NEW DELHI",
    "CENTRE": "NEW DELHI",
    "DISTRICT": "NEW DELHI",
    "NEFT": true,
    "IMPS": true,
    "SWIFT": null,
    "ISO3166": "IN-DL"
  },
  "VTBJ0000002": {
    "BANK": null,
    "IFSC": "VTBJ0000002",
    "MICR": null,
    "BRANCH": "NEW DELHI",
    "ADDRESS": "JSC VTB BANK, TAJ MAHAL HOTEL, LOBBY MEZZANINE FLOOR 1, MANSINGH ROAD NEW DELHI- 110011",
    "STATE": "DELHI",
    "CONTACT": "+9111662210000",
    "UPI": false,
    "RTGS": true,
    "CITY": "NEW DELHI",
    "CENTRE": "New Delhi",
    "DISTRICT": "New Delhi",
    "NEFT": true,
    "IMPS": true,
    "SWIFT": null,
    "ISO3166": "IN-DL"
  }
}